{
  "package": "english",
  "name": "UK - Movies - Live.",
  "groupIndex": 27,
  "totalChannels": 28,
  "channels": [
    {
      "name": "UK: FILM 4 HD  (101-SERVERS)",
      "group": "UK - Movies - Live.",
      "logo": "https://logo.m3uassets.com/film4.png"
    },
    {
      "name": "UK: Horror Channel HD  (101-SERVERS)",
      "group": "UK - Movies - Live.",
      "logo": "https://logo.m3uassets.com/horrorchannel.png"
    },
    {
      "name": "UK: Movies4men HD  (101-SERVERS)",
      "group": "UK - Movies - Live.",
      "logo": "https://logo.m3uassets.com/movies4men.png"
    },
    {
      "name": "UK: Movies4men HD  (101-SERVERS)",
      "group": "UK - Movies - Live.",
      "logo": "https://logo.m3uassets.com/movies4men.png"
    },
    {
      "name": "UK: SKY 1 HD  (101-SERVERS)",
      "group": "UK - Movies - Live.",
      "logo": "https://logo.m3uassets.com/sky1.png"
    },
    {
      "name": "UK: SKY Cinema Action HD  (101-SERVERS)",
      "group": "UK - Movies - Live.",
      "logo": "https://logo.m3uassets.com/skycinemaaction.png"
    },
    {
      "name": "UK: SKY Cinema Comedy FHD  (101-SERVERS)",
      "group": "UK - Movies - Live.",
      "logo": "https://logo.m3uassets.com/skycinemacomedy.png"
    },
    {
      "name": "UK: SKY Cinema Crime & Thriller HD  (101-SERVERS)",
      "group": "UK - Movies - Live.",
      "logo": "http://img-cdn.curl.pk:8880/channels_icon/85315002231.png"
    },
    {
      "name": "UK: SKY Cinema Disney FHD  (101-SERVERS)",
      "group": "UK - Movies - Live.",
      "logo": "https://logo.m3uassets.com/skycinemadisney.png"
    },
    {
      "name": "UK: SKY Cinema Drama & Romance HD  (101-SERVERS)",
      "group": "UK - Movies - Live.",
      "logo": "http://img-cdn.curl.pk:8880/channels_icon/18277087911.png"
    },
    {
      "name": "UK: SKY Cinema Family FHD  (101-SERVERS)",
      "group": "UK - Movies - Live.",
      "logo": "https://logo.m3uassets.com/skycinemafamily.png"
    },
    {
      "name": "UK: SKY Cinema Family HD  (101-SERVERS)",
      "group": "UK - Movies - Live.",
      "logo": "https://logo.m3uassets.com/skycinemafamily.png"
    },
    {
      "name": "UK: SKY Cinema Greats HD  (101-SERVERS)",
      "group": "UK - Movies - Live.",
      "logo": "https://logo.m3uassets.com/skycinemagreats.png"
    },
    {
      "name": "UK: SKY Cinema Premiere HD  (101-SERVERS)",
      "group": "UK - Movies - Live.",
      "logo": "https://logo.m3uassets.com/skycinemapremiere.png"
    },
    {
      "name": "UK: SKY Cinema Premiere FHD  (101-SERVERS)",
      "group": "UK - Movies - Live.",
      "logo": "https://logo.m3uassets.com/skycinemapremiere.png"
    },
    {
      "name": "UK: SKY Cinema Sci-fi & Horror HD  (101-SERVERS)",
      "group": "UK - Movies - Live.",
      "logo": "http://img-cdn.curl.pk:8880/channels_icon/99977077101.png"
    },
    {
      "name": "UK: SKY Cinema Select FHD  (101-SERVERS)",
      "group": "UK - Movies - Live.",
      "logo": "https://logo.m3uassets.com/skycinemaselect.png"
    },
    {
      "name": "UK: SKY Cinema Thriller FHD  (101-SERVERS)",
      "group": "UK - Movies - Live.",
      "logo": "https://logo.m3uassets.com/skycinemathriller.png"
    },
    {
      "name": "UK: SKY Cinema Thriller HD  (101-SERVERS)",
      "group": "UK - Movies - Live.",
      "logo": "https://logo.m3uassets.com/skycinemathriller.png"
    },
    {
      "name": "UK: SKY Movies Select HD  (101-SERVERS)",
      "group": "UK - Movies - Live.",
      "logo": "https://logo.m3uassets.com/skymoviesselect.png"
    },
    {
      "name": "UK: SKY ONE FHD  (101-SERVERS)",
      "group": "UK - Movies - Live.",
      "logo": "https://logo.m3uassets.com/skyone.png"
    },
    {
      "name": "UK: SKY Store 1 HD  (101-SERVERS)",
      "group": "UK - Movies - Live.",
      "logo": "https://logo.m3uassets.com/skystore1.png"
    },
    {
      "name": "UK: SKY Store 2 HD  (101-SERVERS)",
      "group": "UK - Movies - Live.",
      "logo": "https://logo.m3uassets.com/skystore2.png"
    },
    {
      "name": "UK: SKY Witness HD  (101-SERVERS)",
      "group": "UK - Movies - Live.",
      "logo": "https://logo.m3uassets.com/skywitness.png"
    },
    {
      "name": "UK: SONY Movies Christmas HD  (101-SERVERS)",
      "group": "UK - Movies - Live.",
      "logo": "https://logo.m3uassets.com/sonymovieschristmas.png"
    },
    {
      "name": "UK: Sky Cinema Hits HD  (101-SERVERS)",
      "group": "UK - Movies - Live.",
      "logo": "https://logo.m3uassets.com/skycinemahits.png"
    },
    {
      "name": "UK: Sky Hits  (101-SERVERS)",
      "group": "UK - Movies - Live.",
      "logo": "https://logo.m3uassets.com/skyhits.png"
    },
    {
      "name": "UK: TCM Movies HD  (101-SERVERS)",
      "group": "UK - Movies - Live.",
      "logo": "https://logo.m3uassets.com/tcmmovies.png"
    }
  ]
}